{
  "homeGridLogoRows": 2,
  "name": "BIOMA",
  "socialLinks": [
    {
      "link": "https://behance.net/biomaarquitectos",
      "icon": "mdi:behance"
    },
    {
      "link": "https://instagram.com/biomaarquitectos",
      "icon": "mdi:instagram"
    },
    {
      "link": "mailto:asdf@gmail.com",
      "icon": "mdi:email"
    }
  ],
  "homeGridLogoColumns": 8,
  "url": "https://biomaestudio.com",
  "debug": false,
  "cover": "https://res.cloudinary.com/biomaarquitectos/image/upload/c_scale,f_auto,q_auto,w_160/v1715007263/ORANGE_aubo8d.png",
  "cloudinaryName": "biomaarquitectos",
  "description": "ARQUITECTURA. Diseño + branding",
  "repoName": "bioma"
}
